synrecon/__init__.py
synrecon/chem.py
synrecon/cli.py
synrecon/constraints.py
synrecon/elements.py
synrecon/models.py
synrecon/solver.py
synrecon-0.0.1.dist-info/METADATA
synrecon-0.0.1.dist-info/WHEEL
synrecon-0.0.1.dist-info/entry_points.txt
synrecon-0.0.1.dist-info/licenses/LICENSE
synrecon-0.0.1.dist-info/RECORD
