Metadata-Version: 2.4
Name: synrecon
Version: 0.0.1
Summary: Utility for reaction modeling using graph grammar
Project-URL: homepage, https://github.com/TieuLongPhan/synrecon
Project-URL: source, https://github.com/TieuLongPhan/synrecon
Project-URL: issues, https://github.com/TieuLongPhan/synrecon/issues
Project-URL: documentation, https://synrecon.readthedocs.io/en/latest/
Author-email: Tieu Long Phan <tieu@bioinf.uni-leipzig.de>
License-File: LICENSE
Classifier: License :: OSI Approved :: MIT License
Classifier: Operating System :: OS Independent
Classifier: Programming Language :: Python :: 3
Requires-Python: >=3.11
Requires-Dist: pulp>=3.3.0
Requires-Dist: synkit>=1.0.1
Provides-Extra: all
Requires-Dist: numpy>=2.2.0; extra == 'all'
Requires-Dist: pandas>=1.5.3; extra == 'all'
Provides-Extra: docs
Requires-Dist: sphinx-rtd-theme; extra == 'docs'
Requires-Dist: sphinx>=6.0; extra == 'docs'
Requires-Dist: sphinxcontrib-bibtex; extra == 'docs'
